{
  "editor:insert-wikilink": [
    {
      "modifiers": [
        "Mod"
      ],
      "key": "L"
    }
  ],
  "editor:toggle-checklist-status": [],
  "note-composer:split-file": [
    {
      "modifiers": [
        "Mod"
      ],
      "key": "E"
    }
  ],
  "markdown:toggle-preview": [
    {
      "modifiers": [
        "Mod"
      ],
      "key": "R"
    }
  ],
  "graph:open-local": [
    {
      "modifiers": [
        "Mod",
        "Shift"
      ],
      "key": "G"
    }
  ],
  "app:toggle-right-sidebar": [
    {
      "modifiers": [
        "Alt",
        "Mod"
      ],
      "key": "."
    }
  ],
  "app:toggle-left-sidebar": [
    {
      "modifiers": [
        "Alt",
        "Mod"
      ],
      "key": ","
    }
  ],
  "theme:toggle-light-dark": [
    {
      "modifiers": [
        "Alt",
        "Mod"
      ],
      "key": "'"
    }
  ],
  "editor:insert-table": [
    {
      "modifiers": [
        "Alt",
        "Mod"
      ],
      "key": "T"
    }
  ]
}